{"fragmentation_time": 0.9003311, "payload_size": 512, "total_transmission_time": 1777.646, "total_number_of_fragments": 52, "fragments": {"9": {"abort": false, "timeout": 0, "W": "000", "send_time": 2.573517, "rssi": 0, "data": "ð\u00157891212345", "sending_start": 357.9852, "receiver_abort_received": false, "receiver_abort_message": "", "RULE_ID": "1111000", "sending_end": 360.5587, "downlink_enable": false, "ack_received": false, "ack": "", "FCN": "10101", "fragment_size": 12}, "8": {"abort": false, "timeout": 0, "W": "000", "send_time": 2.572662, "rssi": 0, "data": "ð\u00166789123456", "sending_start": 325.259, "receiver_abort_received": false, "receiver_abort_message": "", "RULE_ID": "1111000", "sending_end": 327.8317, "downlink_enable": false, "ack_received": false, "ack": "", "FCN": "10110", "fragment_size": 12}, "18": {"abort": false, "timeout": 0, "W": "000", "send_time": 2.572815, "rssi": 0, "data": "ð\u000c1234567891", "sending_start": 652.5349, "receiver_abort_received": false, "receiver_abort_message": "", "RULE_ID": "1111000", "sending_end": 655.1077, "downlink_enable": false, "ack_received": false, "ack": "", "FCN": "01100", "fragment_size": 12}, "19": {"abort": false, "timeout": 0, "W": "000", "send_time": 2.57489, "rssi": 0, "data": "ð\u000b2123456789", "sending_start": 685.2696, "receiver_abort_received": false, "receiver_abort_message": "", "RULE_ID": "1111000", "sending_end": 687.8445, "downlink_enable": false, "ack_received": false, "ack": "", "FCN": "01011", "fragment_size": 12}, "3": {"abort": false, "timeout": 0, "W": "000", "send_time": 2.575027, "rssi": 0, "data": "ð\u001b9121234567", "sending_start": 161.6438, "receiver_abort_received": false, "receiver_abort_message": "", "RULE_ID": "1111000", "sending_end": 164.2188, "downlink_enable": false, "ack_received": false, "ack": "", "FCN": "11011", "fragment_size": 12}, "36": {"abort": false, "timeout": 0, "W": "001", "send_time": 2.572021, "rssi": 0, "data": "ð92345678912", "sending_start": 1285.008, "receiver_abort_received": false, "receiver_abort_message": "", "RULE_ID": "1111000", "sending_end": 1287.58, "downlink_enable": false, "ack_received": false, "ack": "", "FCN": "11001", "fragment_size": 12}, "37": {"abort": false, "timeout": 0, "W": "001", "send_time": 2.57251, "rssi": 0, "data": "ð83456789121", "sending_start": 1317.757, "receiver_abort_received": false, "receiver_abort_message": "", "RULE_ID": "1111000", "sending_end": 1320.33, "downlink_enable": false, "ack_received": false, "ack": "", "FCN": "11000", "fragment_size": 12}, "34": {"abort": false, "timeout": 0, "W": "001", "send_time": 2.572998, "rssi": 0, "data": "ð;2345678912", "sending_start": 1219.52, "receiver_abort_received": false, "receiver_abort_message": "", "RULE_ID": "1111000", "sending_end": 1222.093, "downlink_enable": false, "ack_received": false, "ack": "", "FCN": "11011", "fragment_size": 12}, "39": {"abort": false, "timeout": 0, "W": "001", "send_time": 2.571899, "rssi": 0, "data": "ð62123456789", "sending_start": 1383.257, "receiver_abort_received": false, "receiver_abort_message": "", "RULE_ID": "1111000", "sending_end": 1385.829, "downlink_enable": false, "ack_received": false, "ack": "", "FCN": "10110", "fragment_size": 12}, "42": {"abort": false, "timeout": 0, "W": "001", "send_time": 2.574585, "rssi": 0, "data": "ð38912123456", "sending_start": 1481.51, "receiver_abort_received": false, "receiver_abort_message": "", "RULE_ID": "1111000", "sending_end": 1484.085, "downlink_enable": false, "ack_received": false, "ack": "", "FCN": "10011", "fragment_size": 12}, "35": {"abort": false, "timeout": 0, "W": "001", "send_time": 2.572144, "rssi": 0, "data": "ð:1234567891", "sending_start": 1252.267, "receiver_abort_received": false, "receiver_abort_message": "", "RULE_ID": "1111000", "sending_end": 1254.839, "downlink_enable": false, "ack_received": false, "ack": "", "FCN": "11010", "fragment_size": 12}, "32": {"abort": false, "timeout": 0, "W": "001", "send_time": 2.571899, "rssi": 0, "data": "ð=4567891212", "sending_start": 1154.035, "receiver_abort_received": false, "receiver_abort_message": "", "RULE_ID": "1111000", "sending_end": 1156.607, "downlink_enable": false, "ack_received": false, "ack": "", "FCN": "11101", "fragment_size": 12}, "33": {"abort": false, "timeout": 0, "W": "001", "send_time": 2.572021, "rssi": 0, "data": "ð<3456789121", "sending_start": 1186.773, "receiver_abort_received": false, "receiver_abort_message": "", "RULE_ID": "1111000", "sending_end": 1189.345, "downlink_enable": false, "ack_received": false, "ack": "", "FCN": "11100", "fragment_size": 12}, "30": {"abort": false, "timeout": 20, "W": "000", "send_time": 45.66223, "rssi": 0, "data": "ð\u00002345678912", "sending_start": 1045.437, "receiver_abort_received": false, "receiver_abort_message": "", "RULE_ID": "1111000", "sending_end": 1091.099, "downlink_enable": true, "ack_received": false, "ack": "", "FCN": "00000", "fragment_size": 12}, "31": {"abort": false, "timeout": 0, "W": "001", "send_time": 2.571899, "rssi": 0, "data": "ð>3456789123", "sending_start": 1121.292, "receiver_abort_received": false, "receiver_abort_message": "", "RULE_ID": "1111000", "sending_end": 1123.864, "downlink_enable": false, "ack_received": false, "ack": "", "FCN": "11110", "fragment_size": 12}, "44": {"abort": false, "timeout": 0, "W": "001", "send_time": 2.575684, "rssi": 0, "data": "ð16789123456", "sending_start": 1547.032, "receiver_abort_received": false, "receiver_abort_message": "", "RULE_ID": "1111000", "sending_end": 1549.608, "downlink_enable": false, "ack_received": false, "ack": "", "FCN": "10001", "fragment_size": 12}, "45": {"abort": false, "timeout": 0, "W": "001", "send_time": 2.572144, "rssi": 0, "data": "ð03456789123", "sending_start": 1579.785, "receiver_abort_received": false, "receiver_abort_message": "", "RULE_ID": "1111000", "sending_end": 1582.358, "downlink_enable": false, "ack_received": false, "ack": "", "FCN": "10000", "fragment_size": 12}, "46": {"abort": false, "timeout": 0, "W": "001", "send_time": 2.57373, "rssi": 0, "data": "ð/4567349121", "sending_start": 1612.544, "receiver_abort_received": false, "receiver_abort_message": "", "RULE_ID": "1111000", "sending_end": 1615.118, "downlink_enable": false, "ack_received": false, "ack": "", "FCN": "01111", "fragment_size": 12}, "41": {"abort": false, "timeout": 0, "W": "001", "send_time": 2.572632, "rssi": 0, "data": "ð49121234567", "sending_start": 1448.762, "receiver_abort_received": false, "receiver_abort_message": "", "RULE_ID": "1111000", "sending_end": 1451.335, "downlink_enable": false, "ack_received": false, "ack": "", "FCN": "10100", "fragment_size": 12}, "40": {"abort": false, "timeout": 0, "W": "001", "send_time": 2.574341, "rssi": 0, "data": "ð51212345678", "sending_start": 1416.008, "receiver_abort_received": false, "receiver_abort_message": "", "RULE_ID": "1111000", "sending_end": 1418.583, "downlink_enable": false, "ack_received": false, "ack": "", "FCN": "10101", "fragment_size": 12}, "43": {"abort": false, "timeout": 0, "W": "001", "send_time": 2.572266, "rssi": 0, "data": "ð27891212345", "sending_start": 1514.266, "receiver_abort_received": false, "receiver_abort_message": "", "RULE_ID": "1111000", "sending_end": 1516.839, "downlink_enable": false, "ack_received": false, "ack": "", "FCN": "10010", "fragment_size": 12}, "38": {"abort": false, "timeout": 0, "W": "001", "send_time": 2.576416, "rssi": 0, "data": "ð72344567891", "sending_start": 1350.507, "receiver_abort_received": false, "receiver_abort_message": "", "RULE_ID": "1111000", "sending_end": 1353.084, "downlink_enable": false, "ack_received": false, "ack": "", "FCN": "10111", "fragment_size": 12}, "27": {"abort": false, "timeout": 0, "W": "000", "send_time": 2.575684, "rssi": 0, "data": "ð\u00035678912123", "sending_start": 947.15, "receiver_abort_received": false, "receiver_abort_message": "", "RULE_ID": "1111000", "sending_end": 949.7257, "downlink_enable": false, "ack_received": false, "ack": "", "FCN": "00011", "fragment_size": 12}, "26": {"abort": false, "timeout": 0, "W": "000", "send_time": 2.572876, "rssi": 0, "data": "ð\u00046789121234", "sending_start": 914.4088, "receiver_abort_received": false, "receiver_abort_message": "", "RULE_ID": "1111000", "sending_end": 916.9816, "downlink_enable": false, "ack_received": false, "ack": "", "FCN": "00100", "fragment_size": 12}, "25": {"abort": false, "timeout": 0, "W": "000", "send_time": 2.574768, "rssi": 0, "data": "ð\u00057891212345", "sending_start": 881.6738, "receiver_abort_received": false, "receiver_abort_message": "", "RULE_ID": "1111000", "sending_end": 884.2485, "downlink_enable": false, "ack_received": false, "ack": "", "FCN": "00101", "fragment_size": 12}, "22": {"abort": false, "timeout": 0, "W": "000", "send_time": 2.571838, "rssi": 0, "data": "ð\u00086789123456", "sending_start": 783.4698, "receiver_abort_received": false, "receiver_abort_message": "", "RULE_ID": "1111000", "sending_end": 786.0416, "downlink_enable": false, "ack_received": false, "ack": "", "FCN": "01000", "fragment_size": 12}, "21": {"abort": false, "timeout": 0, "W": "000", "send_time": 2.574036, "rssi": 0, "data": "ð\t9123456345", "sending_start": 750.7354, "receiver_abort_received": false, "receiver_abort_message": "", "RULE_ID": "1111000", "sending_end": 753.3094, "downlink_enable": false, "ack_received": false, "ack": "", "FCN": "01001", "fragment_size": 12}, "20": {"abort": false, "timeout": 0, "W": "000", "send_time": 2.572388, "rssi": 0, "data": "ð\n1212345678", "sending_start": 718.0003, "receiver_abort_received": false, "receiver_abort_message": "", "RULE_ID": "1111000", "sending_end": 720.5727, "downlink_enable": false, "ack_received": false, "ack": "", "FCN": "01010", "fragment_size": 12}, "24": {"abort": false, "timeout": 0, "W": "000", "send_time": 2.572937, "rssi": 0, "data": "ð\u00068912123456", "sending_start": 848.9367, "receiver_abort_received": false, "receiver_abort_message": "", "RULE_ID": "1111000", "sending_end": 851.5097, "downlink_enable": false, "ack_received": false, "ack": "", "FCN": "00110", "fragment_size": 12}, "23": {"abort": false, "timeout": 0, "W": "000", "send_time": 2.573181, "rssi": 0, "data": "ð\u00077341234567", "sending_start": 816.1989, "receiver_abort_received": false, "receiver_abort_message": "", "RULE_ID": "1111000", "sending_end": 818.772, "downlink_enable": false, "ack_received": false, "ack": "", "FCN": "00111", "fragment_size": 12}, "5": {"abort": false, "timeout": 0, "W": "000", "send_time": 2.576614, "rssi": 0, "data": "ð\u00197891212345", "sending_start": 227.0889, "receiver_abort_received": false, "receiver_abort_message": "", "RULE_ID": "1111000", "sending_end": 229.6655, "downlink_enable": false, "ack_received": false, "ack": "", "FCN": "11001", "fragment_size": 12}, "4": {"abort": false, "timeout": 0, "W": "000", "send_time": 2.571991, "rssi": 0, "data": "ð\u001a8912123456", "sending_start": 194.3727, "receiver_abort_received": false, "receiver_abort_message": "", "RULE_ID": "1111000", "sending_end": 196.9447, "downlink_enable": false, "ack_received": false, "ack": "", "FCN": "11010", "fragment_size": 12}, "7": {"abort": false, "timeout": 0, "W": "000", "send_time": 2.574921, "rssi": 0, "data": "ð\u00175678912345", "sending_start": 292.5395, "receiver_abort_received": false, "receiver_abort_message": "", "RULE_ID": "1111000", "sending_end": 295.1144, "downlink_enable": false, "ack_received": false, "ack": "", "FCN": "10111", "fragment_size": 12}, "47": {"abort": false, "timeout": 0, "W": "001", "send_time": 2.571777, "rssi": 0, "data": "ð.2345678912", "sending_start": 1645.303, "receiver_abort_received": false, "receiver_abort_message": "", "RULE_ID": "1111000", "sending_end": 1647.874, "downlink_enable": false, "ack_received": false, "ack": "", "FCN": "01110", "fragment_size": 12}, "29": {"abort": false, "timeout": 0, "W": "000", "send_time": 2.639648, "rssi": 0, "data": "ð\u00013456789121", "sending_start": 1012.633, "receiver_abort_received": false, "receiver_abort_message": "", "RULE_ID": "1111000", "sending_end": 1015.272, "downlink_enable": false, "ack_received": false, "ack": "", "FCN": "00001", "fragment_size": 12}, "28": {"abort": false, "timeout": 0, "W": "000", "send_time": 2.57196, "rssi": 0, "data": "ð\u00024567891212", "sending_start": 979.8926, "receiver_abort_received": false, "receiver_abort_message": "", "RULE_ID": "1111000", "sending_end": 982.4646, "downlink_enable": false, "ack_received": false, "ack": "", "FCN": "00010", "fragment_size": 12}, "48": {"abort": false, "timeout": 0, "W": "001", "send_time": 2.574219, "rssi": 0, "data": "ð-3456789123", "sending_start": 1678.055, "receiver_abort_received": false, "receiver_abort_message": "", "RULE_ID": "1111000", "sending_end": 1680.629, "downlink_enable": false, "ack_received": false, "ack": "", "FCN": "01101", "fragment_size": 12}, "49": {"abort": false, "timeout": 0, "W": "001", "send_time": 2.572021, "rssi": 0, "data": "ð,4567891212", "sending_start": 1710.818, "receiver_abort_received": false, "receiver_abort_message": "", "RULE_ID": "1111000", "sending_end": 1713.389, "downlink_enable": false, "ack_received": false, "ack": "", "FCN": "01100", "fragment_size": 12}, "50": {"abort": false, "timeout": 0, "W": "001", "send_time": 2.578003, "rssi": 0, "data": "ð+3456789121", "sending_start": 1743.578, "receiver_abort_received": false, "receiver_abort_message": "", "RULE_ID": "1111000", "sending_end": 1746.156, "downlink_enable": false, "ack_received": false, "ack": "", "FCN": "01011", "fragment_size": 12}, "51": {"abort": false, "timeout": 45, "W": "001", "send_time": 34.51941, "rssi": -48, "data": "ð?23", "sending_start": 1776.34, "receiver_abort_received": false, "receiver_abort_message": "", "RULE_ID": "1111000", "sending_end": 1810.859, "downlink_enable": true, "ack_received": true, "ack": "ð0\u0000\u0000\u0000\u0000\u0000\u0000", "FCN": "11111", "fragment_size": 4}, "14": {"abort": false, "timeout": 0, "W": "000", "send_time": 2.572449, "rssi": 0, "data": "ð\u00106789121234", "sending_start": 521.6142, "receiver_abort_received": false, "receiver_abort_message": "", "RULE_ID": "1111000", "sending_end": 524.1866, "downlink_enable": false, "ack_received": false, "ack": "", "FCN": "10000", "fragment_size": 12}, "15": {"abort": false, "timeout": 0, "W": "000", "send_time": 2.574036, "rssi": 0, "data": "ð\u000f4567891212", "sending_start": 554.3383, "receiver_abort_received": false, "receiver_abort_message": "", "RULE_ID": "1111000", "sending_end": 556.9123, "downlink_enable": false, "ack_received": false, "ack": "", "FCN": "01111", "fragment_size": 12}, "16": {"abort": false, "timeout": 0, "W": "000", "send_time": 2.572754, "rssi": 0, "data": "ð\u000e3456789121", "sending_start": 587.0689, "receiver_abort_received": false, "receiver_abort_message": "", "RULE_ID": "1111000", "sending_end": 589.6417, "downlink_enable": false, "ack_received": false, "ack": "", "FCN": "01110", "fragment_size": 12}, "6": {"abort": false, "timeout": 0, "W": "000", "send_time": 2.572601, "rssi": 0, "data": "ð\u00186789121234", "sending_start": 259.8161, "receiver_abort_received": false, "receiver_abort_message": "", "RULE_ID": "1111000", "sending_end": 262.3887, "downlink_enable": false, "ack_received": false, "ack": "", "FCN": "11000", "fragment_size": 12}, "1": {"abort": false, "timeout": 0, "W": "000", "send_time": 2.574326, "rssi": 0, "data": "ð\u001d2123456789", "sending_start": 96.20445, "receiver_abort_received": false, "receiver_abort_message": "", "RULE_ID": "1111000", "sending_end": 98.77878, "downlink_enable": false, "ack_received": false, "ack": "", "FCN": "11101", "fragment_size": 12}, "17": {"abort": false, "timeout": 0, "W": "000", "send_time": 2.573547, "rssi": 0, "data": "ð\r2345678912", "sending_start": 619.8091, "receiver_abort_received": false, "receiver_abort_message": "", "RULE_ID": "1111000", "sending_end": 622.3826, "downlink_enable": false, "ack_received": false, "ack": "", "FCN": "01101", "fragment_size": 12}, "10": {"abort": false, "timeout": 0, "W": "000", "send_time": 2.57254, "rssi": 0, "data": "ð\u00146789121234", "sending_start": 390.7102, "receiver_abort_received": false, "receiver_abort_message": "", "RULE_ID": "1111000", "sending_end": 393.2828, "downlink_enable": false, "ack_received": false, "ack": "", "FCN": "10100", "fragment_size": 12}, "2": {"abort": false, "timeout": 0, "W": "000", "send_time": 2.572113, "rssi": 0, "data": "ð\u001c1212345678", "sending_start": 128.9206, "receiver_abort_received": false, "receiver_abort_message": "", "RULE_ID": "1111000", "sending_end": 131.4927, "downlink_enable": false, "ack_received": false, "ack": "", "FCN": "11100", "fragment_size": 12}, "11": {"abort": false, "timeout": 0, "W": "000", "send_time": 2.575287, "rssi": 0, "data": "ð\u00135678912123", "sending_start": 423.4356, "receiver_abort_received": false, "receiver_abort_message": "", "RULE_ID": "1111000", "sending_end": 426.0109, "downlink_enable": false, "ack_received": false, "ack": "", "FCN": "10011", "fragment_size": 12}, "12": {"abort": false, "timeout": 0, "W": "000", "send_time": 2.572449, "rssi": 0, "data": "ð\u00124567891234", "sending_start": 456.1582, "receiver_abort_received": false, "receiver_abort_message": "", "RULE_ID": "1111000", "sending_end": 458.7306, "downlink_enable": false, "ack_received": false, "ack": "", "FCN": "10010", "fragment_size": 12}, "13": {"abort": false, "timeout": 0, "W": "000", "send_time": 2.57309, "rssi": 0, "data": "ð\u00115678912345", "sending_start": 488.8862, "receiver_abort_received": false, "receiver_abort_message": "", "RULE_ID": "1111000", "sending_end": 491.4593, "downlink_enable": false, "ack_received": false, "ack": "", "FCN": "10001", "fragment_size": 12}, "0": {"abort": false, "timeout": 0, "W": "000", "send_time": 2.573051, "rssi": 0, "data": "ð\u001e1234567891", "sending_start": 63.48364, "receiver_abort_received": false, "receiver_abort_message": "", "RULE_ID": "1111000", "sending_end": 66.05669, "downlink_enable": false, "ack_received": false, "ack": "", "FCN": "11110", "fragment_size": 12}}, "tx_status_ok": true}