{"fragmentation_time": 0.2033406, "payload_size": 150, "total_transmission_time": 155.0523, "total_number_of_fragments": 16, "fragments": {"14": {"abort": false, "timeout": 0, "W": "01", "send_time": 2.572021, "rssi": 0, "data": "\r56789121234", "sending_start": 449.7961, "receiver_abort_received": false, "receiver_abort_message": "", "RULE_ID": "00", "sending_end": 452.3681, "downlink_enable": false, "ack_received": false, "ack": "", "FCN": "101", "fragment_size": 12}, "15": {"abort": false, "timeout": 45, "W": "01", "send_time": 35.13974, "rssi": -68, "data": "\u000f9121234", "sending_start": 472.4292, "receiver_abort_received": false, "receiver_abort_message": "", "RULE_ID": "00", "sending_end": 507.5689, "downlink_enable": true, "ack_received": true, "ack": "\u000c\u0000\u0000\u0000\u0000\u0000\u0000\u0000", "FCN": "111", "fragment_size": 8}, "5": {"abort": false, "timeout": 0, "W": "00", "send_time": 3.572296, "rssi": 0, "data": "\u000112345678912", "sending_start": 167.3429, "receiver_abort_received": false, "receiver_abort_message": "", "RULE_ID": "00", "sending_end": 170.9152, "downlink_enable": false, "ack_received": false, "ack": "", "FCN": "001", "fragment_size": 12}, "4": {"abort": false, "timeout": 0, "W": "00", "send_time": 2.573303, "rssi": 0, "data": "\u000212345678912", "sending_start": 144.6378, "receiver_abort_received": false, "receiver_abort_message": "", "RULE_ID": "00", "sending_end": 147.2111, "downlink_enable": false, "ack_received": false, "ack": "", "FCN": "010", "fragment_size": 12}, "10": {"abort": false, "timeout": 0, "W": "01", "send_time": 2.573181, "rssi": 0, "data": "\u000b56789121234", "sending_start": 326.1714, "receiver_abort_received": false, "receiver_abort_message": "", "RULE_ID": "00", "sending_end": 328.7446, "downlink_enable": false, "ack_received": false, "ack": "", "FCN": "011", "fragment_size": 12}, "11": {"abort": false, "timeout": 0, "W": "01", "send_time": 2.572876, "rssi": 0, "data": "\n56789123456", "sending_start": 348.8865, "receiver_abort_received": false, "receiver_abort_message": "", "RULE_ID": "00", "sending_end": 351.4594, "downlink_enable": false, "ack_received": false, "ack": "", "FCN": "010", "fragment_size": 12}, "7": {"abort": false, "timeout": 0, "W": "01", "send_time": 2.571167, "rssi": 0, "data": "\u000e34567891234", "sending_start": 256.9034, "receiver_abort_received": false, "receiver_abort_message": "", "RULE_ID": "00", "sending_end": 259.4746, "downlink_enable": false, "ack_received": false, "ack": "", "FCN": "110", "fragment_size": 12}, "6": {"abort": false, "timeout": 20, "W": "00", "send_time": 45.66542, "rssi": 0, "data": "\u000012345678912", "sending_start": 191.0784, "receiver_abort_received": false, "receiver_abort_message": "", "RULE_ID": "00", "sending_end": 236.7438, "downlink_enable": true, "ack_received": false, "ack": "", "FCN": "000", "fragment_size": 12}, "1": {"abort": false, "timeout": 0, "W": "00", "send_time": 3.573257, "rssi": 0, "data": "\u000512345678912", "sending_start": 75.47784, "receiver_abort_received": false, "receiver_abort_message": "", "RULE_ID": "00", "sending_end": 79.0511, "downlink_enable": false, "ack_received": false, "ack": "", "FCN": "101", "fragment_size": 12}, "0": {"abort": false, "timeout": 0, "W": "00", "send_time": 2.572239, "rssi": 0, "data": "\u000612345678912", "sending_start": 52.77531, "receiver_abort_received": false, "receiver_abort_message": "", "RULE_ID": "00", "sending_end": 55.34755, "downlink_enable": false, "ack_received": false, "ack": "", "FCN": "110", "fragment_size": 12}, "3": {"abort": false, "timeout": 0, "W": "00", "send_time": 2.571953, "rssi": 0, "data": "\u000312345678912", "sending_start": 121.9066, "receiver_abort_received": false, "receiver_abort_message": "", "RULE_ID": "00", "sending_end": 124.4786, "downlink_enable": false, "ack_received": false, "ack": "", "FCN": "011", "fragment_size": 12}, "2": {"abort": false, "timeout": 0, "W": "00", "send_time": 2.572899, "rssi": 0, "data": "\u000412345678912", "sending_start": 99.20221, "receiver_abort_received": false, "receiver_abort_message": "", "RULE_ID": "00", "sending_end": 101.7751, "downlink_enable": false, "ack_received": false, "ack": "", "FCN": "100", "fragment_size": 12}, "12": {"abort": false, "timeout": 0, "W": "01", "send_time": 2.572815, "rssi": 0, "data": "\t78912345678", "sending_start": 371.6004, "receiver_abort_received": false, "receiver_abort_message": "", "RULE_ID": "00", "sending_end": 374.1732, "downlink_enable": false, "ack_received": false, "ack": "", "FCN": "001", "fragment_size": 12}, "13": {"abort": false, "timeout": 45, "W": "01", "send_time": 35.22321, "rssi": -67, "data": "\u000f9121234", "sending_start": 394.3458, "receiver_abort_received": false, "receiver_abort_message": "", "RULE_ID": "00", "sending_end": 429.569, "downlink_enable": true, "ack_received": true, "ack": "\nø\u0000\u0000\u0000\u0000\u0000\u0000", "FCN": "111", "fragment_size": 8}, "9": {"abort": false, "timeout": 0, "W": "01", "send_time": 3.644409, "rssi": 0, "data": "\u000c56789121234", "sending_start": 302.3577, "receiver_abort_received": false, "receiver_abort_message": "", "RULE_ID": "00", "sending_end": 306.0022, "downlink_enable": false, "ack_received": false, "ack": "", "FCN": "100", "fragment_size": 12}, "8": {"abort": false, "timeout": 0, "W": "01", "send_time": 2.572266, "rssi": 0, "data": "\r56789121234", "sending_start": 279.6408, "receiver_abort_received": false, "receiver_abort_message": "", "RULE_ID": "00", "sending_end": 282.2131, "downlink_enable": false, "ack_received": false, "ack": "", "FCN": "101", "fragment_size": 12}}, "tx_status_ok": true}